cephalon/__init__.py
cephalon/api/__init__.py
cephalon/api/common/__init__.py
cephalon/api/common/base_schemas.py
cephalon/api/common/response_errors.py
cephalon/api/module/__init__.py
cephalon/api/module/auth.py
cephalon/api/schema/__init__.py
cephalon/api/schema/auth.py
cephalon/cli.py
cephalon/console.py
cephalon/core.py
cephalon/credentials.py
cephalon/meta.py
cephalon/path.py
cephalon/utils.py
cephalon/validate.py
cephalon_client-0.1.0.dist-info/METADATA
cephalon_client-0.1.0.dist-info/WHEEL
cephalon_client-0.1.0.dist-info/entry_points.txt
cephalon_client-0.1.0.dist-info/RECORD
